mercedtodo/__init__.py
mercedtodo/__main__.py
mercedtodo/cli.py
mercedtodo/config.py
mercedtodo/database.py
mercedtodo/logic.py
mercedtodo/models.py
mercedtodo/tui.py
mercedtodo-0.1.4.dist-info/METADATA
mercedtodo-0.1.4.dist-info/WHEEL
mercedtodo-0.1.4.dist-info/entry_points.txt
mercedtodo-0.1.4.dist-info/RECORD
