Metadata-Version: 2.4
Name: mercedtodo
Version: 0.1.4
Summary: A CLI and TUI todo list manager
Project-URL: Homepage, https://github.com/AlexMercedCoder/mercedtodo-cli
Project-URL: Repository, https://github.com/AlexMercedCoder/mercedtodo-cli
Project-URL: Issues, https://github.com/AlexMercedCoder/mercedtodo-cli/issues
Author-email: Alex Merced <alexmerced@alexmerced.com>
License: MIT
Keywords: cli,productivity,task-manager,todo,tui
Classifier: Development Status :: 4 - Beta
Classifier: Environment :: Console
Classifier: Intended Audience :: Developers
Classifier: Intended Audience :: End Users/Desktop
Classifier: License :: OSI Approved :: MIT License
Classifier: Programming Language :: Python :: 3
Classifier: Programming Language :: Python :: 3.10
Classifier: Programming Language :: Python :: 3.11
Classifier: Programming Language :: Python :: 3.12
Classifier: Topic :: Office/Business :: Scheduling
Classifier: Topic :: Utilities
Requires-Python: >=3.10
Requires-Dist: platformdirs>=4.0.0
Requires-Dist: textual>=0.40.0
Requires-Dist: typer>=0.9.0
